<annotation>
	<folder>Apple Red Delicious</folder>
	<filename>152red applee01831152.png</filename>
	<path>D:\GUNADARMA\SKRIPSI\PROJECT\DATASET\Apple Red Delicious\152red applee01831152.png</path>
	<source>
		<database>Unknown</database>
	</source>
	<size>
		<width>480</width>
		<height>322</height>
		<depth>3</depth>
	</size>
	<segmented>0</segmented>
	<object>
		<name>Apel Red Delicious</name>
		<pose>Unspecified</pose>
		<truncated>0</truncated>
		<difficult>0</difficult>
		<bndbox>
			<xmin>219</xmin>
			<ymin>56</ymin>
			<xmax>376</xmax>
			<ymax>180</ymax>
		</bndbox>
	</object>
	<object>
		<name>Apel Red Delicious</name>
		<pose>Unspecified</pose>
		<truncated>0</truncated>
		<difficult>0</difficult>
		<bndbox>
			<xmin>33</xmin>
			<ymin>135</ymin>
			<xmax>166</xmax>
			<ymax>253</ymax>
		</bndbox>
	</object>
	<object>
		<name>Apel Red Delicious</name>
		<pose>Unspecified</pose>
		<truncated>0</truncated>
		<difficult>0</difficult>
		<bndbox>
			<xmin>153</xmin>
			<ymin>157</ymin>
			<xmax>284</xmax>
			<ymax>281</ymax>
		</bndbox>
	</object>
	<object>
		<name>Apel Red Delicious</name>
		<pose>Unspecified</pose>
		<truncated>1</truncated>
		<difficult>0</difficult>
		<bndbox>
			<xmin>352</xmin>
			<ymin>2</ymin>
			<xmax>480</xmax>
			<ymax>107</ymax>
		</bndbox>
	</object>
	<object>
		<name>Apel Red Delicious</name>
		<pose>Unspecified</pose>
		<truncated>0</truncated>
		<difficult>0</difficult>
		<bndbox>
			<xmin>272</xmin>
			<ymin>156</ymin>
			<xmax>406</xmax>
			<ymax>292</ymax>
		</bndbox>
	</object>
	<object>
		<name>Apel Red Delicious</name>
		<pose>Unspecified</pose>
		<truncated>1</truncated>
		<difficult>0</difficult>
		<bndbox>
			<xmin>397</xmin>
			<ymin>164</ymin>
			<xmax>480</xmax>
			<ymax>291</ymax>
		</bndbox>
	</object>
</annotation>
